pypi_cleanup/LICENSE
pypi_cleanup/__init__.py
pypi_cleanup/__version__.py
pypi_cleanup-0.1.8.dist-info/METADATA
pypi_cleanup-0.1.8.dist-info/WHEEL
pypi_cleanup-0.1.8.dist-info/entry_points.txt
pypi_cleanup-0.1.8.dist-info/namespace_packages.txt
pypi_cleanup-0.1.8.dist-info/top_level.txt
pypi_cleanup-0.1.8.dist-info/zip-safe
pypi_cleanup-0.1.8.dist-info/RECORD
