Metadata-Version: 2.1
Name: pypi-cleanup
Version: 0.1.8
Summary: PyPI Bulk Release Version Cleanup Utility
Home-page: https://github.com/arcivanov/pypi-cleanup
Author: Arcadiy Ivanov
Author-email: arcadiy@ivanov.biz
Maintainer: Arcadiy Ivanov
Maintainer-email: arcadiy@ivanov.biz
License: Apache License, Version 2.0
Project-URL: Bug Tracker, https://github.com/arcivanov/pypi-cleanup/issues
Project-URL: Documentation, https://github.com/arcivanov/pypi-cleanup
Project-URL: Source Code, https://github.com/arcivanov/pypi-cleanup
Keywords: PyPI cleanup build dev tool release version
Classifier: Programming Language :: Python
Classifier: Programming Language :: Python :: Implementation :: CPython
Classifier: Programming Language :: Python :: Implementation :: PyPy
Classifier: Programming Language :: Python :: 3
Classifier: Programming Language :: Python :: 3.7
Classifier: Programming Language :: Python :: 3.8
Classifier: Programming Language :: Python :: 3.9
Classifier: Programming Language :: Python :: 3.10
Classifier: Programming Language :: Python :: 3.11
Classifier: Programming Language :: Python :: 3.12
Classifier: Operating System :: MacOS :: MacOS X
Classifier: Operating System :: POSIX :: Linux
Classifier: Operating System :: Microsoft :: Windows
Classifier: Operating System :: OS Independent
Classifier: Development Status :: 5 - Production/Stable
Classifier: Environment :: Console
Classifier: Intended Audience :: Developers
Classifier: License :: OSI Approved :: Apache Software License
Classifier: Topic :: Software Development :: Build Tools
Requires-Python: >=3.7
Requires-Dist: requests~=2.23
